navigation_mdp/__init__.py
navigation_mdp/_version.py
navigation_mdp/class_.py
navigation_mdp/dynamics.py
navigation_mdp/features.py
navigation_mdp/plotting.py
navigation_mdp/reward.py
navigation_mdp/state.py
navigation_mdp/utils.py
navigation_mdp/version.py
navigation_mdp/world.py
navigation_mdp-1.2.dist-info/LICENSE
navigation_mdp-1.2.dist-info/METADATA
navigation_mdp-1.2.dist-info/WHEEL
navigation_mdp-1.2.dist-info/dependency_links.txt
navigation_mdp-1.2.dist-info/top_level.txt
navigation_mdp-1.2.dist-info/RECORD
