Metadata-Version: 2.1
Name: navigation-mdp
Version: 1.2
Summary: A lightweight library for defining navigation grid world
Home-page: https://github.com/yrevar/navigation_mdp
Author: Yagnesh Revar
Author-email: mailto.yagnesh+github@gmail.com
Keywords: Markov Decision Process,MDP,Navigation
Classifier: Programming Language :: Python :: 3
Classifier: License :: OSI Approved :: Apache Software License
Classifier: Operating System :: OS Independent
Requires-Python: >=3.6
License-File: LICENSE
Requires-Dist: navigation-vis
